{
  "description": "",
  "key": "e39aa035-4053-465a-a318-98e25cd2b4c0",
  "tags": [
    {
      "key": "e5804d3d-b8fa-4806-a7b8-f6bf7bd4e31f",
      "name": "name",
      "value": "django",
      "labelerLogin": "",
      "createdAt": "2025-02-17 15:54:21.971657+00:00",
      "updatedAt": "2025-02-21 19:10:53.201661+00:00"
    },
    {
      "key": "3ea3e9b8-6ad4-48f1-ae34-c18c8def185a",
      "name": "labels",
      "value": [
        {
          "label_id": 0,
          "name": "Person",
          "color": "#c06060",
          "type": "any"
        }
      ],
      "labelerLogin": "",
      "createdAt": "2025-02-17 15:54:21.971657+00:00",
      "updatedAt": "2025-02-21 19:10:53.201661+00:00"
    }
  ],
  "objects": [
    {
      "key": "881f1cb4-32ee-45c8-972f-8782bca8afcc",
      "classTitle": "Person",
      "tags": [
        {
          "key": "b36c1b98-63f2-460f-a61f-5cd8841321a2",
          "name": "occluded",
          "value": "false",
          "labelerLogin": "",
          "createdAt": "2025-02-17 15:54:21.971657+00:00",
          "updatedAt": "2025-02-21 19:10:53.201661+00:00"
        },
        {
          "key": "0f90b5b4-0ea0-4e40-9c24-fca65823e1ca",
          "name": "keyframe",
          "value": "false",
          "labelerLogin": "",
          "createdAt": "2025-02-17 15:54:21.971657+00:00",
          "updatedAt": "2025-02-21 19:10:53.201661+00:00"
        }
      ],
      "objects": [],
      "figures": [],
      "labelerLogin": "",
      "createdAt": "2025-02-17 15:54:21.971657+00:00",
      "updatedAt": "2025-02-21 19:10:53.201661+00:00"
    },
    {
      "key": "ff7ac162-c834-4d5c-95a9-88ca3eab056e",
      "classTitle": "Person",
      "tags": [
        {
          "key": "3e2fad54-765a-4a6c-9ad8-60760f2a7be3",
          "name": "occluded",
          "value": "false",
          "labelerLogin": "",
          "createdAt": "2025-02-17 15:54:21.971657+00:00",
          "updatedAt": "2025-02-21 19:10:53.201661+00:00"
        },
        {
          "key": "9341251e-aeb9-4639-9243-d3d55906bebb",
          "name": "keyframe",
          "value": "false",
          "labelerLogin": "",
          "createdAt": "2025-02-17 15:54:21.971657+00:00",
          "updatedAt": "2025-02-21 19:10:53.201661+00:00"
        }
      ],
      "objects": [],
      "figures": [],
      "labelerLogin": "",
      "createdAt": "2025-02-17 15:54:21.971657+00:00",
      "updatedAt": "2025-02-21 19:10:53.201661+00:00"
    },
    {
      "key": "9d47e71a-6b4c-43be-bf30-23ca690d3e54",
      "classTitle": "Person",
      "tags": [
        {
          "key": "5ded3b9e-7f43-4fb8-a4c0-2499737ac387",
          "name": "occluded",
          "value": "false",
          "labelerLogin": "",
          "createdAt": "2025-02-17 15:54:21.971657+00:00",
          "updatedAt": "2025-02-21 19:10:53.201661+00:00"
        },
        {
          "key": "8f1566ce-6333-4e62-a29d-234f7fcfc417",
          "name": "keyframe",
          "value": "false",
          "labelerLogin": "",
          "createdAt": "2025-02-17 15:54:21.971657+00:00",
          "updatedAt": "2025-02-21 19:10:53.201661+00:00"
        }
      ],
      "objects": [],
      "figures": [],
      "labelerLogin": "",
      "createdAt": "2025-02-17 15:54:21.971657+00:00",
      "updatedAt": "2025-02-21 19:10:53.201661+00:00"
    },
    {
      "key": "4f9504ff-9399-4e3b-98a6-292d0a781002",
      "classTitle": "Person",
      "tags": [
        {
          "key": "288fc61f-3922-4bd2-930d-c2520712b782",
          "name": "occluded",
          "value": "false",
          "labelerLogin": "",
          "createdAt": "2025-02-17 15:54:21.971657+00:00",
          "updatedAt": "2025-02-21 19:10:53.201661+00:00"
        },
        {
          "key": "589c8e11-3046-40e5-ba17-76561d10554e",
          "name": "keyframe",
          "value": "false",
          "labelerLogin": "",
          "createdAt": "2025-02-17 15:54:21.971657+00:00",
          "updatedAt": "2025-02-21 19:10:53.201661+00:00"
        }
      ],
      "objects": [],
      "figures": [],
      "labelerLogin": "",
      "createdAt": "2025-02-17 15:54:21.971657+00:00",
      "updatedAt": "2025-02-21 19:10:53.201661+00:00"
    },
    {
      "key": "6afb3de2-34d1-407f-8168-96f0e780e607",
      "classTitle": "Person",
      "tags": [
        {
          "key": "2410fbb0-350f-493f-a211-a75386470c09",
          "name": "occluded",
          "value": "false",
          "labelerLogin": "",
          "createdAt": "2025-02-17 15:54:21.971657+00:00",
          "updatedAt": "2025-02-21 19:10:53.201661+00:00"
        },
        {
          "key": "b24398eb-5055-4408-8ec1-f718e2f10234",
          "name": "keyframe",
          "value": "false",
          "labelerLogin": "",
          "createdAt": "2025-02-17 15:54:21.971657+00:00",
          "updatedAt": "2025-02-21 19:10:53.201661+00:00"
        }
      ],
      "objects": [],
      "figures": [],
      "labelerLogin": "",
      "createdAt": "2025-02-17 15:54:21.971657+00:00",
      "updatedAt": "2025-02-21 19:10:53.201661+00:00"
    }
  ],
  "figures": [
    {
      "key": "30386818-2604-4b4e-9eaa-c1fc1a7973d6",
      "objectKey": "881f1cb4-32ee-45c8-972f-8782bca8afcc",
      "geometryType": "cuboid_3d",
      "geometry": {
        "position": {
          "x": 7.2,
          "y": -5.71,
          "z": -1.29
        },
        "rotation": {
          "x": 0.0,
          "y": 0.0,
          "z": 0.0
        },
        "dimensions": {
          "x": 0.75,
          "y": 0.76,
          "z": 1.64
        }
      },
      "labelerLogin": "",
      "createdAt": "2025-02-17 15:54:21.971657+00:00",
      "updatedAt": "2025-02-21 19:10:53.201661+00:00"
    },
    {
      "key": "257fbd70-55c7-46fb-8cc7-ee08e9dcd1c5",
      "objectKey": "ff7ac162-c834-4d5c-95a9-88ca3eab056e",
      "geometryType": "cuboid_3d",
      "geometry": {
        "position": {
          "x": 10.82,
          "y": -1.45,
          "z": -1.27
        },
        "rotation": {
          "x": 0.0,
          "y": 0.0,
          "z": 0.0
        },
        "dimensions": {
          "x": 0.75,
          "y": 0.87,
          "z": 1.64
        }
      },
      "labelerLogin": "",
      "createdAt": "2025-02-17 15:54:21.971657+00:00",
      "updatedAt": "2025-02-21 19:10:53.201661+00:00"
    },
    {
      "key": "caa0a014-bbfc-49fc-bd73-0006e8eb13fb",
      "objectKey": "9d47e71a-6b4c-43be-bf30-23ca690d3e54",
      "geometryType": "cuboid_3d",
      "geometry": {
        "position": {
          "x": 2.34,
          "y": -2.11,
          "z": -1.3
        },
        "rotation": {
          "x": 0.0,
          "y": 0.0,
          "z": 0.0
        },
        "dimensions": {
          "x": 0.75,
          "y": 0.87,
          "z": 1.64
        }
      },
      "labelerLogin": "",
      "createdAt": "2025-02-17 15:54:21.971657+00:00",
      "updatedAt": "2025-02-21 19:10:53.201661+00:00"
    },
    {
      "key": "38efa490-f92d-4fdc-9530-28f3b490f5f5",
      "objectKey": "4f9504ff-9399-4e3b-98a6-292d0a781002",
      "geometryType": "cuboid_3d",
      "geometry": {
        "position": {
          "x": 4.98,
          "y": -5.53,
          "z": -1.32
        },
        "rotation": {
          "x": 0.0,
          "y": 0.0,
          "z": 0.0
        },
        "dimensions": {
          "x": 0.75,
          "y": 0.87,
          "z": 1.64
        }
      },
      "labelerLogin": "",
      "createdAt": "2025-02-17 15:54:21.971657+00:00",
      "updatedAt": "2025-02-21 19:10:53.201661+00:00"
    },
    {
      "key": "a0a3ec79-6a08-4e9d-94fb-c9b22e40c3d7",
      "objectKey": "6afb3de2-34d1-407f-8168-96f0e780e607",
      "geometryType": "cuboid_3d",
      "geometry": {
        "position": {
          "x": 3.07,
          "y": 0.57,
          "z": -1.41
        },
        "rotation": {
          "x": 0.0,
          "y": 0.0,
          "z": 0.0
        },
        "dimensions": {
          "x": 0.75,
          "y": 0.87,
          "z": 1.64
        }
      },
      "labelerLogin": "",
      "createdAt": "2025-02-17 15:54:21.971657+00:00",
      "updatedAt": "2025-02-21 19:10:53.201661+00:00"
    }
  ]
}