{
  "description": "",
  "key": "d0db4a17-f537-4171-af7d-3816cde00ee8",
  "tags": [
    {
      "key": "62cdf8d6-ea8b-4907-ab9c-ef69fb4473f5",
      "name": "name",
      "value": "django",
      "labelerLogin": "",
      "createdAt": "2025-02-17 15:54:21.971657+00:00",
      "updatedAt": "2025-02-21 19:10:53.201661+00:00"
    },
    {
      "key": "fdc1f42b-222a-42ca-90f4-ed4c4ff10d80",
      "name": "labels",
      "value": [
        {
          "label_id": 0,
          "name": "Person",
          "color": "#c06060",
          "type": "any"
        }
      ],
      "labelerLogin": "",
      "createdAt": "2025-02-17 15:54:21.971657+00:00",
      "updatedAt": "2025-02-21 19:10:53.201661+00:00"
    }
  ],
  "objects": [
    {
      "key": "881f1cb4-32ee-45c8-972f-8782bca8afcc",
      "classTitle": "Person",
      "tags": [
        {
          "key": "b2157d57-9a96-4f71-ba51-47e33ef2afd5",
          "name": "occluded",
          "value": "false",
          "labelerLogin": "",
          "createdAt": "2025-02-17 15:54:21.971657+00:00",
          "updatedAt": "2025-02-21 19:10:53.201661+00:00"
        },
        {
          "key": "bcc8ab29-47d9-4bd1-957b-0e608142e881",
          "name": "keyframe",
          "value": "false",
          "labelerLogin": "",
          "createdAt": "2025-02-17 15:54:21.971657+00:00",
          "updatedAt": "2025-02-21 19:10:53.201661+00:00"
        }
      ],
      "objects": [],
      "figures": [],
      "labelerLogin": "",
      "createdAt": "2025-02-17 15:54:21.971657+00:00",
      "updatedAt": "2025-02-21 19:10:53.201661+00:00"
    },
    {
      "key": "ff7ac162-c834-4d5c-95a9-88ca3eab056e",
      "classTitle": "Person",
      "tags": [
        {
          "key": "6a2b5322-30c3-4ee1-a7cf-2a331c59cc4d",
          "name": "occluded",
          "value": "false",
          "labelerLogin": "",
          "createdAt": "2025-02-17 15:54:21.971657+00:00",
          "updatedAt": "2025-02-21 19:10:53.201661+00:00"
        },
        {
          "key": "ce4faa48-40bf-45d3-bb32-f3ce1eeaf695",
          "name": "keyframe",
          "value": "false",
          "labelerLogin": "",
          "createdAt": "2025-02-17 15:54:21.971657+00:00",
          "updatedAt": "2025-02-21 19:10:53.201661+00:00"
        }
      ],
      "objects": [],
      "figures": [],
      "labelerLogin": "",
      "createdAt": "2025-02-17 15:54:21.971657+00:00",
      "updatedAt": "2025-02-21 19:10:53.201661+00:00"
    },
    {
      "key": "9d47e71a-6b4c-43be-bf30-23ca690d3e54",
      "classTitle": "Person",
      "tags": [
        {
          "key": "569486ea-0d15-4050-9c65-80f6d7b54ae1",
          "name": "occluded",
          "value": "false",
          "labelerLogin": "",
          "createdAt": "2025-02-17 15:54:21.971657+00:00",
          "updatedAt": "2025-02-21 19:10:53.201661+00:00"
        },
        {
          "key": "76e52dc1-689f-4de5-bfbc-126526d1936f",
          "name": "keyframe",
          "value": "false",
          "labelerLogin": "",
          "createdAt": "2025-02-17 15:54:21.971657+00:00",
          "updatedAt": "2025-02-21 19:10:53.201661+00:00"
        }
      ],
      "objects": [],
      "figures": [],
      "labelerLogin": "",
      "createdAt": "2025-02-17 15:54:21.971657+00:00",
      "updatedAt": "2025-02-21 19:10:53.201661+00:00"
    },
    {
      "key": "4f9504ff-9399-4e3b-98a6-292d0a781002",
      "classTitle": "Person",
      "tags": [
        {
          "key": "d51b3054-1577-423b-8e69-ec26cae6ed9d",
          "name": "occluded",
          "value": "false",
          "labelerLogin": "",
          "createdAt": "2025-02-17 15:54:21.971657+00:00",
          "updatedAt": "2025-02-21 19:10:53.201661+00:00"
        },
        {
          "key": "d92c1dfe-8e4b-4434-a460-ac08b09a2f5a",
          "name": "keyframe",
          "value": "false",
          "labelerLogin": "",
          "createdAt": "2025-02-17 15:54:21.971657+00:00",
          "updatedAt": "2025-02-21 19:10:53.201661+00:00"
        }
      ],
      "objects": [],
      "figures": [],
      "labelerLogin": "",
      "createdAt": "2025-02-17 15:54:21.971657+00:00",
      "updatedAt": "2025-02-21 19:10:53.201661+00:00"
    },
    {
      "key": "6afb3de2-34d1-407f-8168-96f0e780e607",
      "classTitle": "Person",
      "tags": [
        {
          "key": "764bf334-c108-45b8-81f7-981964eae42d",
          "name": "occluded",
          "value": "false",
          "labelerLogin": "",
          "createdAt": "2025-02-17 15:54:21.971657+00:00",
          "updatedAt": "2025-02-21 19:10:53.201661+00:00"
        },
        {
          "key": "2e4c8344-9a69-4984-b1ce-32930df4515c",
          "name": "keyframe",
          "value": "false",
          "labelerLogin": "",
          "createdAt": "2025-02-17 15:54:21.971657+00:00",
          "updatedAt": "2025-02-21 19:10:53.201661+00:00"
        }
      ],
      "objects": [],
      "figures": [],
      "labelerLogin": "",
      "createdAt": "2025-02-17 15:54:21.971657+00:00",
      "updatedAt": "2025-02-21 19:10:53.201661+00:00"
    }
  ],
  "figures": [
    {
      "key": "f49bc49b-8bca-47d1-8519-38b7944b1290",
      "objectKey": "881f1cb4-32ee-45c8-972f-8782bca8afcc",
      "geometryType": "cuboid_3d",
      "geometry": {
        "position": {
          "x": 2.76,
          "y": 0.37,
          "z": -1.29
        },
        "rotation": {
          "x": 0.0,
          "y": 0.0,
          "z": 0.0
        },
        "dimensions": {
          "x": 0.75,
          "y": 0.76,
          "z": 1.64
        }
      },
      "labelerLogin": "",
      "createdAt": "2025-02-17 15:54:21.971657+00:00",
      "updatedAt": "2025-02-21 19:10:53.201661+00:00"
    },
    {
      "key": "3c4674ba-9a65-4a5d-903f-bb0cfd2a8cd7",
      "objectKey": "ff7ac162-c834-4d5c-95a9-88ca3eab056e",
      "geometryType": "cuboid_3d",
      "geometry": {
        "position": {
          "x": 2.4,
          "y": -1.69,
          "z": -1.27
        },
        "rotation": {
          "x": 0.0,
          "y": 0.0,
          "z": 0.0
        },
        "dimensions": {
          "x": 0.75,
          "y": 0.87,
          "z": 1.64
        }
      },
      "labelerLogin": "",
      "createdAt": "2025-02-17 15:54:21.971657+00:00",
      "updatedAt": "2025-02-21 19:10:53.201661+00:00"
    },
    {
      "key": "6b103581-6276-46c5-a49c-1824c8d482f2",
      "objectKey": "9d47e71a-6b4c-43be-bf30-23ca690d3e54",
      "geometryType": "cuboid_3d",
      "geometry": {
        "position": {
          "x": 10.06,
          "y": -1.88,
          "z": -1.3
        },
        "rotation": {
          "x": 0.0,
          "y": 0.0,
          "z": 0.0
        },
        "dimensions": {
          "x": 0.75,
          "y": 0.87,
          "z": 1.64
        }
      },
      "labelerLogin": "",
      "createdAt": "2025-02-17 15:54:21.971657+00:00",
      "updatedAt": "2025-02-21 19:10:53.201661+00:00"
    },
    {
      "key": "2550821c-170e-4bec-8fe9-3116494e9637",
      "objectKey": "4f9504ff-9399-4e3b-98a6-292d0a781002",
      "geometryType": "cuboid_3d",
      "geometry": {
        "position": {
          "x": 9.84,
          "y": 1.23,
          "z": -1.32
        },
        "rotation": {
          "x": 0.0,
          "y": 0.0,
          "z": 0.0
        },
        "dimensions": {
          "x": 0.75,
          "y": 0.87,
          "z": 1.64
        }
      },
      "labelerLogin": "",
      "createdAt": "2025-02-17 15:54:21.971657+00:00",
      "updatedAt": "2025-02-21 19:10:53.201661+00:00"
    },
    {
      "key": "f7572f1c-46e1-4bfb-8a38-d0d6803a6a35",
      "objectKey": "6afb3de2-34d1-407f-8168-96f0e780e607",
      "geometryType": "cuboid_3d",
      "geometry": {
        "position": {
          "x": 7.3,
          "y": -5.82,
          "z": -1.41
        },
        "rotation": {
          "x": 0.0,
          "y": 0.0,
          "z": 0.0
        },
        "dimensions": {
          "x": 0.75,
          "y": 0.87,
          "z": 1.64
        }
      },
      "labelerLogin": "",
      "createdAt": "2025-02-17 15:54:21.971657+00:00",
      "updatedAt": "2025-02-21 19:10:53.201661+00:00"
    }
  ]
}