{
  "description": "",
  "key": "c71b2140-51f9-47cd-8532-31e94e0937e1",
  "tags": [
    {
      "key": "3c0c0df2-c88b-4022-b2da-b5622bc4489a",
      "name": "name",
      "value": "django",
      "labelerLogin": "",
      "createdAt": "2025-02-17 15:54:21.971657+00:00",
      "updatedAt": "2025-02-21 19:10:53.201661+00:00"
    },
    {
      "key": "7ec97aaf-2100-4f78-9d32-d6f3631e957d",
      "name": "labels",
      "value": [
        {
          "label_id": 0,
          "name": "Person",
          "color": "#c06060",
          "type": "any"
        }
      ],
      "labelerLogin": "",
      "createdAt": "2025-02-17 15:54:21.971657+00:00",
      "updatedAt": "2025-02-21 19:10:53.201661+00:00"
    }
  ],
  "objects": [
    {
      "key": "881f1cb4-32ee-45c8-972f-8782bca8afcc",
      "classTitle": "Person",
      "tags": [
        {
          "key": "6835bf84-4163-4945-af16-457b7f2af13d",
          "name": "occluded",
          "value": "false",
          "labelerLogin": "",
          "createdAt": "2025-02-17 15:54:21.971657+00:00",
          "updatedAt": "2025-02-21 19:10:53.201661+00:00"
        },
        {
          "key": "33cddd10-cdb8-4da4-82f7-51ddf92e012a",
          "name": "keyframe",
          "value": "false",
          "labelerLogin": "",
          "createdAt": "2025-02-17 15:54:21.971657+00:00",
          "updatedAt": "2025-02-21 19:10:53.201661+00:00"
        }
      ],
      "objects": [],
      "figures": [],
      "labelerLogin": "",
      "createdAt": "2025-02-17 15:54:21.971657+00:00",
      "updatedAt": "2025-02-21 19:10:53.201661+00:00"
    },
    {
      "key": "ff7ac162-c834-4d5c-95a9-88ca3eab056e",
      "classTitle": "Person",
      "tags": [
        {
          "key": "d8ddb6ab-c95d-45a6-93a2-224d45cc54a2",
          "name": "occluded",
          "value": "false",
          "labelerLogin": "",
          "createdAt": "2025-02-17 15:54:21.971657+00:00",
          "updatedAt": "2025-02-21 19:10:53.201661+00:00"
        },
        {
          "key": "743c0cab-f8bf-425b-ba51-c4e776e4bd70",
          "name": "keyframe",
          "value": "false",
          "labelerLogin": "",
          "createdAt": "2025-02-17 15:54:21.971657+00:00",
          "updatedAt": "2025-02-21 19:10:53.201661+00:00"
        }
      ],
      "objects": [],
      "figures": [],
      "labelerLogin": "",
      "createdAt": "2025-02-17 15:54:21.971657+00:00",
      "updatedAt": "2025-02-21 19:10:53.201661+00:00"
    },
    {
      "key": "9d47e71a-6b4c-43be-bf30-23ca690d3e54",
      "classTitle": "Person",
      "tags": [
        {
          "key": "e4326ea4-c002-4939-9c98-c7418afa55a5",
          "name": "occluded",
          "value": "false",
          "labelerLogin": "",
          "createdAt": "2025-02-17 15:54:21.971657+00:00",
          "updatedAt": "2025-02-21 19:10:53.201661+00:00"
        },
        {
          "key": "006fe623-aec0-4e6e-925f-46676e50f1b1",
          "name": "keyframe",
          "value": "false",
          "labelerLogin": "",
          "createdAt": "2025-02-17 15:54:21.971657+00:00",
          "updatedAt": "2025-02-21 19:10:53.201661+00:00"
        }
      ],
      "objects": [],
      "figures": [],
      "labelerLogin": "",
      "createdAt": "2025-02-17 15:54:21.971657+00:00",
      "updatedAt": "2025-02-21 19:10:53.201661+00:00"
    },
    {
      "key": "4f9504ff-9399-4e3b-98a6-292d0a781002",
      "classTitle": "Person",
      "tags": [
        {
          "key": "fafb7605-b113-40d5-9d17-075ae3e751bd",
          "name": "occluded",
          "value": "false",
          "labelerLogin": "",
          "createdAt": "2025-02-17 15:54:21.971657+00:00",
          "updatedAt": "2025-02-21 19:10:53.201661+00:00"
        },
        {
          "key": "4b5da5b9-32b8-4903-9154-e68eb1190080",
          "name": "keyframe",
          "value": "false",
          "labelerLogin": "",
          "createdAt": "2025-02-17 15:54:21.971657+00:00",
          "updatedAt": "2025-02-21 19:10:53.201661+00:00"
        }
      ],
      "objects": [],
      "figures": [],
      "labelerLogin": "",
      "createdAt": "2025-02-17 15:54:21.971657+00:00",
      "updatedAt": "2025-02-21 19:10:53.201661+00:00"
    },
    {
      "key": "6afb3de2-34d1-407f-8168-96f0e780e607",
      "classTitle": "Person",
      "tags": [
        {
          "key": "c5450540-64ac-42ab-8d42-0e547344ea49",
          "name": "occluded",
          "value": "false",
          "labelerLogin": "",
          "createdAt": "2025-02-17 15:54:21.971657+00:00",
          "updatedAt": "2025-02-21 19:10:53.201661+00:00"
        },
        {
          "key": "756c6264-7134-498e-8564-6e83a1ed6ab4",
          "name": "keyframe",
          "value": "false",
          "labelerLogin": "",
          "createdAt": "2025-02-17 15:54:21.971657+00:00",
          "updatedAt": "2025-02-21 19:10:53.201661+00:00"
        }
      ],
      "objects": [],
      "figures": [],
      "labelerLogin": "",
      "createdAt": "2025-02-17 15:54:21.971657+00:00",
      "updatedAt": "2025-02-21 19:10:53.201661+00:00"
    }
  ],
  "figures": [
    {
      "key": "cb12f15a-4000-44f1-81bf-1d712dfb40f5",
      "objectKey": "881f1cb4-32ee-45c8-972f-8782bca8afcc",
      "geometryType": "cuboid_3d",
      "geometry": {
        "position": {
          "x": 2.82,
          "y": 0.56,
          "z": -1.29
        },
        "rotation": {
          "x": 0.0,
          "y": 0.0,
          "z": 0.0
        },
        "dimensions": {
          "x": 0.75,
          "y": 0.76,
          "z": 1.64
        }
      },
      "labelerLogin": "",
      "createdAt": "2025-02-17 15:54:21.971657+00:00",
      "updatedAt": "2025-02-21 19:10:53.201661+00:00"
    },
    {
      "key": "95d74dc8-371a-4298-9c30-1d33561be3a8",
      "objectKey": "ff7ac162-c834-4d5c-95a9-88ca3eab056e",
      "geometryType": "cuboid_3d",
      "geometry": {
        "position": {
          "x": 2.07,
          "y": -2.21,
          "z": -1.27
        },
        "rotation": {
          "x": 0.0,
          "y": 0.0,
          "z": 0.0
        },
        "dimensions": {
          "x": 0.75,
          "y": 0.87,
          "z": 1.64
        }
      },
      "labelerLogin": "",
      "createdAt": "2025-02-17 15:54:21.971657+00:00",
      "updatedAt": "2025-02-21 19:10:53.201661+00:00"
    },
    {
      "key": "4c651c1b-7427-4283-ac74-14c207faf66e",
      "objectKey": "9d47e71a-6b4c-43be-bf30-23ca690d3e54",
      "geometryType": "cuboid_3d",
      "geometry": {
        "position": {
          "x": 10.93,
          "y": -1.73,
          "z": -1.3
        },
        "rotation": {
          "x": 0.0,
          "y": 0.0,
          "z": 0.0
        },
        "dimensions": {
          "x": 0.75,
          "y": 0.87,
          "z": 1.64
        }
      },
      "labelerLogin": "",
      "createdAt": "2025-02-17 15:54:21.971657+00:00",
      "updatedAt": "2025-02-21 19:10:53.201661+00:00"
    },
    {
      "key": "6794e288-0a60-4a36-9cb2-17ca49e80106",
      "objectKey": "4f9504ff-9399-4e3b-98a6-292d0a781002",
      "geometryType": "cuboid_3d",
      "geometry": {
        "position": {
          "x": 9.87,
          "y": 0.85,
          "z": -1.32
        },
        "rotation": {
          "x": 0.0,
          "y": 0.0,
          "z": 0.0
        },
        "dimensions": {
          "x": 0.75,
          "y": 0.87,
          "z": 1.64
        }
      },
      "labelerLogin": "",
      "createdAt": "2025-02-17 15:54:21.971657+00:00",
      "updatedAt": "2025-02-21 19:10:53.201661+00:00"
    },
    {
      "key": "5a264f34-2db8-40a4-bf1b-3439459a42cb",
      "objectKey": "6afb3de2-34d1-407f-8168-96f0e780e607",
      "geometryType": "cuboid_3d",
      "geometry": {
        "position": {
          "x": 7.27,
          "y": -5.89,
          "z": -1.41
        },
        "rotation": {
          "x": 0.0,
          "y": 0.0,
          "z": 0.0
        },
        "dimensions": {
          "x": 0.75,
          "y": 0.87,
          "z": 1.64
        }
      },
      "labelerLogin": "",
      "createdAt": "2025-02-17 15:54:21.971657+00:00",
      "updatedAt": "2025-02-21 19:10:53.201661+00:00"
    }
  ]
}