{
  "description": "",
  "key": "61145a72-3c26-4d12-bcdc-3b901657c429",
  "tags": [
    {
      "key": "fb151202-a924-4f65-a8a4-b229c93c5a9c",
      "name": "name",
      "value": "django",
      "labelerLogin": "",
      "createdAt": "2025-02-17 15:54:21.971657+00:00",
      "updatedAt": "2025-02-21 19:10:53.201661+00:00"
    },
    {
      "key": "03fa5b2c-df6a-4a2b-9683-82bb8c6c007a",
      "name": "labels",
      "value": [
        {
          "label_id": 0,
          "name": "Person",
          "color": "#c06060",
          "type": "any"
        }
      ],
      "labelerLogin": "",
      "createdAt": "2025-02-17 15:54:21.971657+00:00",
      "updatedAt": "2025-02-21 19:10:53.201661+00:00"
    }
  ],
  "objects": [
    {
      "key": "881f1cb4-32ee-45c8-972f-8782bca8afcc",
      "classTitle": "Person",
      "tags": [
        {
          "key": "61f7410c-c0e2-491f-b755-a8b9f872a481",
          "name": "occluded",
          "value": "false",
          "labelerLogin": "",
          "createdAt": "2025-02-17 15:54:21.971657+00:00",
          "updatedAt": "2025-02-21 19:10:53.201661+00:00"
        },
        {
          "key": "c11643f0-c281-4b01-88ff-d6c7658ad85f",
          "name": "keyframe",
          "value": "false",
          "labelerLogin": "",
          "createdAt": "2025-02-17 15:54:21.971657+00:00",
          "updatedAt": "2025-02-21 19:10:53.201661+00:00"
        }
      ],
      "objects": [],
      "figures": [],
      "labelerLogin": "",
      "createdAt": "2025-02-17 15:54:21.971657+00:00",
      "updatedAt": "2025-02-21 19:10:53.201661+00:00"
    },
    {
      "key": "ff7ac162-c834-4d5c-95a9-88ca3eab056e",
      "classTitle": "Person",
      "tags": [
        {
          "key": "1a6e4b84-7f7a-47ac-a46e-c0fcb2c554de",
          "name": "occluded",
          "value": "false",
          "labelerLogin": "",
          "createdAt": "2025-02-17 15:54:21.971657+00:00",
          "updatedAt": "2025-02-21 19:10:53.201661+00:00"
        },
        {
          "key": "f7cc8b22-ed66-4b04-a384-d2a8b1d6213e",
          "name": "keyframe",
          "value": "false",
          "labelerLogin": "",
          "createdAt": "2025-02-17 15:54:21.971657+00:00",
          "updatedAt": "2025-02-21 19:10:53.201661+00:00"
        }
      ],
      "objects": [],
      "figures": [],
      "labelerLogin": "",
      "createdAt": "2025-02-17 15:54:21.971657+00:00",
      "updatedAt": "2025-02-21 19:10:53.201661+00:00"
    },
    {
      "key": "9d47e71a-6b4c-43be-bf30-23ca690d3e54",
      "classTitle": "Person",
      "tags": [
        {
          "key": "3e927210-8d7c-4dab-bd54-90502ea48b1f",
          "name": "occluded",
          "value": "false",
          "labelerLogin": "",
          "createdAt": "2025-02-17 15:54:21.971657+00:00",
          "updatedAt": "2025-02-21 19:10:53.201661+00:00"
        },
        {
          "key": "d989ad04-5c48-4927-9165-5aff5f9c2935",
          "name": "keyframe",
          "value": "false",
          "labelerLogin": "",
          "createdAt": "2025-02-17 15:54:21.971657+00:00",
          "updatedAt": "2025-02-21 19:10:53.201661+00:00"
        }
      ],
      "objects": [],
      "figures": [],
      "labelerLogin": "",
      "createdAt": "2025-02-17 15:54:21.971657+00:00",
      "updatedAt": "2025-02-21 19:10:53.201661+00:00"
    },
    {
      "key": "4f9504ff-9399-4e3b-98a6-292d0a781002",
      "classTitle": "Person",
      "tags": [
        {
          "key": "62b4bf19-611b-4bf4-8e7e-dae3c0564f2e",
          "name": "occluded",
          "value": "false",
          "labelerLogin": "",
          "createdAt": "2025-02-17 15:54:21.971657+00:00",
          "updatedAt": "2025-02-21 19:10:53.201661+00:00"
        },
        {
          "key": "7f594efb-91c4-4d41-ba2c-62d237eaf8fb",
          "name": "keyframe",
          "value": "false",
          "labelerLogin": "",
          "createdAt": "2025-02-17 15:54:21.971657+00:00",
          "updatedAt": "2025-02-21 19:10:53.201661+00:00"
        }
      ],
      "objects": [],
      "figures": [],
      "labelerLogin": "",
      "createdAt": "2025-02-17 15:54:21.971657+00:00",
      "updatedAt": "2025-02-21 19:10:53.201661+00:00"
    },
    {
      "key": "6afb3de2-34d1-407f-8168-96f0e780e607",
      "classTitle": "Person",
      "tags": [
        {
          "key": "c814bc9c-ce32-4f6f-a722-267253556295",
          "name": "occluded",
          "value": "false",
          "labelerLogin": "",
          "createdAt": "2025-02-17 15:54:21.971657+00:00",
          "updatedAt": "2025-02-21 19:10:53.201661+00:00"
        },
        {
          "key": "94133a52-ac58-474d-95e3-c4c5cb8a889b",
          "name": "keyframe",
          "value": "false",
          "labelerLogin": "",
          "createdAt": "2025-02-17 15:54:21.971657+00:00",
          "updatedAt": "2025-02-21 19:10:53.201661+00:00"
        }
      ],
      "objects": [],
      "figures": [],
      "labelerLogin": "",
      "createdAt": "2025-02-17 15:54:21.971657+00:00",
      "updatedAt": "2025-02-21 19:10:53.201661+00:00"
    }
  ],
  "figures": [
    {
      "key": "bc34b463-ac6e-40d0-a426-d8bb157bc1ad",
      "objectKey": "881f1cb4-32ee-45c8-972f-8782bca8afcc",
      "geometryType": "cuboid_3d",
      "geometry": {
        "position": {
          "x": 6.94,
          "y": -5.43,
          "z": -1.29
        },
        "rotation": {
          "x": 0.0,
          "y": 0.0,
          "z": 0.0
        },
        "dimensions": {
          "x": 0.75,
          "y": 0.76,
          "z": 1.64
        }
      },
      "labelerLogin": "",
      "createdAt": "2025-02-17 15:54:21.971657+00:00",
      "updatedAt": "2025-02-21 19:10:53.201661+00:00"
    },
    {
      "key": "d885df01-b194-42c9-99fd-bf9a019e8694",
      "objectKey": "ff7ac162-c834-4d5c-95a9-88ca3eab056e",
      "geometryType": "cuboid_3d",
      "geometry": {
        "position": {
          "x": 10.56,
          "y": -1.25,
          "z": -1.27
        },
        "rotation": {
          "x": 0.0,
          "y": 0.0,
          "z": 0.0
        },
        "dimensions": {
          "x": 0.75,
          "y": 0.87,
          "z": 1.64
        }
      },
      "labelerLogin": "",
      "createdAt": "2025-02-17 15:54:21.971657+00:00",
      "updatedAt": "2025-02-21 19:10:53.201661+00:00"
    },
    {
      "key": "3196118f-e939-44ba-abc4-3fafa5955ce7",
      "objectKey": "9d47e71a-6b4c-43be-bf30-23ca690d3e54",
      "geometryType": "cuboid_3d",
      "geometry": {
        "position": {
          "x": 2.3,
          "y": -2.22,
          "z": -1.3
        },
        "rotation": {
          "x": 0.0,
          "y": 0.0,
          "z": 0.0
        },
        "dimensions": {
          "x": 0.75,
          "y": 0.87,
          "z": 1.64
        }
      },
      "labelerLogin": "",
      "createdAt": "2025-02-17 15:54:21.971657+00:00",
      "updatedAt": "2025-02-21 19:10:53.201661+00:00"
    },
    {
      "key": "ecef80f6-9c22-4ce9-a3e5-ab513ba9b6c8",
      "objectKey": "4f9504ff-9399-4e3b-98a6-292d0a781002",
      "geometryType": "cuboid_3d",
      "geometry": {
        "position": {
          "x": 4.87,
          "y": -5.6,
          "z": -1.32
        },
        "rotation": {
          "x": 0.0,
          "y": 0.0,
          "z": 0.0
        },
        "dimensions": {
          "x": 0.75,
          "y": 0.87,
          "z": 1.64
        }
      },
      "labelerLogin": "",
      "createdAt": "2025-02-17 15:54:21.971657+00:00",
      "updatedAt": "2025-02-21 19:10:53.201661+00:00"
    },
    {
      "key": "6467b390-beaa-43e9-8e76-39fd1c1e6d7b",
      "objectKey": "6afb3de2-34d1-407f-8168-96f0e780e607",
      "geometryType": "cuboid_3d",
      "geometry": {
        "position": {
          "x": 2.99,
          "y": 0.69,
          "z": -1.41
        },
        "rotation": {
          "x": 0.0,
          "y": 0.0,
          "z": 0.0
        },
        "dimensions": {
          "x": 0.75,
          "y": 0.87,
          "z": 1.64
        }
      },
      "labelerLogin": "",
      "createdAt": "2025-02-17 15:54:21.971657+00:00",
      "updatedAt": "2025-02-21 19:10:53.201661+00:00"
    }
  ]
}