{
  "description": "",
  "key": "895df07c-cc64-436d-ad7c-1e25b5c9f140",
  "tags": [
    {
      "key": "834482ec-a6dd-47c6-844c-dc1079fdf596",
      "name": "name",
      "value": "django",
      "labelerLogin": "",
      "createdAt": "2025-02-17 15:54:21.971657+00:00",
      "updatedAt": "2025-02-21 19:10:53.201661+00:00"
    },
    {
      "key": "80043b55-9a3f-430d-95b8-99c2b34dc700",
      "name": "labels",
      "value": [
        {
          "label_id": 0,
          "name": "Person",
          "color": "#c06060",
          "type": "any"
        }
      ],
      "labelerLogin": "",
      "createdAt": "2025-02-17 15:54:21.971657+00:00",
      "updatedAt": "2025-02-21 19:10:53.201661+00:00"
    }
  ],
  "objects": [
    {
      "key": "881f1cb4-32ee-45c8-972f-8782bca8afcc",
      "classTitle": "Person",
      "tags": [
        {
          "key": "ae7d1aac-d5aa-4073-a1c8-8893670f94fe",
          "name": "occluded",
          "value": "false",
          "labelerLogin": "",
          "createdAt": "2025-02-17 15:54:21.971657+00:00",
          "updatedAt": "2025-02-21 19:10:53.201661+00:00"
        },
        {
          "key": "45eb6850-0fee-452f-8abc-c5c8ffbde0c7",
          "name": "keyframe",
          "value": "false",
          "labelerLogin": "",
          "createdAt": "2025-02-17 15:54:21.971657+00:00",
          "updatedAt": "2025-02-21 19:10:53.201661+00:00"
        }
      ],
      "objects": [],
      "figures": [],
      "labelerLogin": "",
      "createdAt": "2025-02-17 15:54:21.971657+00:00",
      "updatedAt": "2025-02-21 19:10:53.201661+00:00"
    },
    {
      "key": "ff7ac162-c834-4d5c-95a9-88ca3eab056e",
      "classTitle": "Person",
      "tags": [
        {
          "key": "95293219-a92f-4f52-bf8d-16d84ebd93e6",
          "name": "occluded",
          "value": "false",
          "labelerLogin": "",
          "createdAt": "2025-02-17 15:54:21.971657+00:00",
          "updatedAt": "2025-02-21 19:10:53.201661+00:00"
        },
        {
          "key": "ae4bef6e-828f-4ec3-bde5-1ea865ba450e",
          "name": "keyframe",
          "value": "false",
          "labelerLogin": "",
          "createdAt": "2025-02-17 15:54:21.971657+00:00",
          "updatedAt": "2025-02-21 19:10:53.201661+00:00"
        }
      ],
      "objects": [],
      "figures": [],
      "labelerLogin": "",
      "createdAt": "2025-02-17 15:54:21.971657+00:00",
      "updatedAt": "2025-02-21 19:10:53.201661+00:00"
    },
    {
      "key": "9d47e71a-6b4c-43be-bf30-23ca690d3e54",
      "classTitle": "Person",
      "tags": [
        {
          "key": "25c7a2be-e0f0-4672-9d0d-ca8f0e7dce0b",
          "name": "occluded",
          "value": "false",
          "labelerLogin": "",
          "createdAt": "2025-02-17 15:54:21.971657+00:00",
          "updatedAt": "2025-02-21 19:10:53.201661+00:00"
        },
        {
          "key": "3e047d22-f9cf-4db1-a6ae-b6a561abb028",
          "name": "keyframe",
          "value": "false",
          "labelerLogin": "",
          "createdAt": "2025-02-17 15:54:21.971657+00:00",
          "updatedAt": "2025-02-21 19:10:53.201661+00:00"
        }
      ],
      "objects": [],
      "figures": [],
      "labelerLogin": "",
      "createdAt": "2025-02-17 15:54:21.971657+00:00",
      "updatedAt": "2025-02-21 19:10:53.201661+00:00"
    },
    {
      "key": "4f9504ff-9399-4e3b-98a6-292d0a781002",
      "classTitle": "Person",
      "tags": [
        {
          "key": "6ef46f32-368e-4a34-a576-6a35a9b7d95f",
          "name": "occluded",
          "value": "false",
          "labelerLogin": "",
          "createdAt": "2025-02-17 15:54:21.971657+00:00",
          "updatedAt": "2025-02-21 19:10:53.201661+00:00"
        },
        {
          "key": "201ac5d0-eab2-4dc5-9947-255f284788f4",
          "name": "keyframe",
          "value": "false",
          "labelerLogin": "",
          "createdAt": "2025-02-17 15:54:21.971657+00:00",
          "updatedAt": "2025-02-21 19:10:53.201661+00:00"
        }
      ],
      "objects": [],
      "figures": [],
      "labelerLogin": "",
      "createdAt": "2025-02-17 15:54:21.971657+00:00",
      "updatedAt": "2025-02-21 19:10:53.201661+00:00"
    },
    {
      "key": "6afb3de2-34d1-407f-8168-96f0e780e607",
      "classTitle": "Person",
      "tags": [
        {
          "key": "8cdde0cc-5ba4-43e8-a39b-af9c2c6235ee",
          "name": "occluded",
          "value": "false",
          "labelerLogin": "",
          "createdAt": "2025-02-17 15:54:21.971657+00:00",
          "updatedAt": "2025-02-21 19:10:53.201661+00:00"
        },
        {
          "key": "a961c606-7c4b-436e-9185-380db4020a6b",
          "name": "keyframe",
          "value": "false",
          "labelerLogin": "",
          "createdAt": "2025-02-17 15:54:21.971657+00:00",
          "updatedAt": "2025-02-21 19:10:53.201661+00:00"
        }
      ],
      "objects": [],
      "figures": [],
      "labelerLogin": "",
      "createdAt": "2025-02-17 15:54:21.971657+00:00",
      "updatedAt": "2025-02-21 19:10:53.201661+00:00"
    }
  ],
  "figures": [
    {
      "key": "1e466842-3b4c-45f7-b469-b47fc939314b",
      "objectKey": "881f1cb4-32ee-45c8-972f-8782bca8afcc",
      "geometryType": "cuboid_3d",
      "geometry": {
        "position": {
          "x": 2.77,
          "y": 0.39,
          "z": -1.29
        },
        "rotation": {
          "x": 0.0,
          "y": 0.0,
          "z": 0.0
        },
        "dimensions": {
          "x": 0.75,
          "y": 0.76,
          "z": 1.64
        }
      },
      "labelerLogin": "",
      "createdAt": "2025-02-17 15:54:21.971657+00:00",
      "updatedAt": "2025-02-21 19:10:53.201661+00:00"
    },
    {
      "key": "d86178ce-da9c-4092-9bd6-94eeb2334ea6",
      "objectKey": "ff7ac162-c834-4d5c-95a9-88ca3eab056e",
      "geometryType": "cuboid_3d",
      "geometry": {
        "position": {
          "x": 2.39,
          "y": -1.69,
          "z": -1.27
        },
        "rotation": {
          "x": 0.0,
          "y": 0.0,
          "z": 0.0
        },
        "dimensions": {
          "x": 0.75,
          "y": 0.87,
          "z": 1.64
        }
      },
      "labelerLogin": "",
      "createdAt": "2025-02-17 15:54:21.971657+00:00",
      "updatedAt": "2025-02-21 19:10:53.201661+00:00"
    },
    {
      "key": "979f3cfc-3724-48d6-b786-43c4603c248e",
      "objectKey": "9d47e71a-6b4c-43be-bf30-23ca690d3e54",
      "geometryType": "cuboid_3d",
      "geometry": {
        "position": {
          "x": 10.11,
          "y": -1.88,
          "z": -1.3
        },
        "rotation": {
          "x": 0.0,
          "y": 0.0,
          "z": 0.0
        },
        "dimensions": {
          "x": 0.75,
          "y": 0.87,
          "z": 1.64
        }
      },
      "labelerLogin": "",
      "createdAt": "2025-02-17 15:54:21.971657+00:00",
      "updatedAt": "2025-02-21 19:10:53.201661+00:00"
    },
    {
      "key": "1be930c1-ab75-4c9c-920b-a0cb53ee6093",
      "objectKey": "4f9504ff-9399-4e3b-98a6-292d0a781002",
      "geometryType": "cuboid_3d",
      "geometry": {
        "position": {
          "x": 9.67,
          "y": 1.16,
          "z": -1.32
        },
        "rotation": {
          "x": 0.0,
          "y": 0.0,
          "z": 0.0
        },
        "dimensions": {
          "x": 0.75,
          "y": 0.87,
          "z": 1.64
        }
      },
      "labelerLogin": "",
      "createdAt": "2025-02-17 15:54:21.971657+00:00",
      "updatedAt": "2025-02-21 19:10:53.201661+00:00"
    },
    {
      "key": "b7dc486e-1521-4943-a907-f924561ecfb4",
      "objectKey": "6afb3de2-34d1-407f-8168-96f0e780e607",
      "geometryType": "cuboid_3d",
      "geometry": {
        "position": {
          "x": 7.29,
          "y": -5.85,
          "z": -1.41
        },
        "rotation": {
          "x": 0.0,
          "y": 0.0,
          "z": 0.0
        },
        "dimensions": {
          "x": 0.75,
          "y": 0.87,
          "z": 1.64
        }
      },
      "labelerLogin": "",
      "createdAt": "2025-02-17 15:54:21.971657+00:00",
      "updatedAt": "2025-02-21 19:10:53.201661+00:00"
    }
  ]
}